TxtMagic/__init__.py
TxtMagic/animation.py
TxtMagic/colorify.py
TxtMagic/emojify.py
TxtMagic/fontify.py
tests/__init__.py
tests/test_colorify.py
tests/test_emojify.py
tests/test_fontify.py
txtmagic-0.1.5.dist-info/licenses/LICENSE
txtmagic-0.1.5.dist-info/METADATA
txtmagic-0.1.5.dist-info/WHEEL
txtmagic-0.1.5.dist-info/top_level.txt
txtmagic-0.1.5.dist-info/RECORD
