Metadata-Version: 2.4
Name: TxtMagic
Version: 0.1.5
Summary: A Python package for adding style, emojis, and colors to your text effortlessly! 🎨✨
Home-page: https://github.com/Pooja-Velmurugen
Author: Pooja V
Author-email: poojavelm@gmail.com
Classifier: Programming Language :: Python :: 3
Classifier: License :: OSI Approved :: MIT License
Requires-Python: >=3.0
License-File: LICENSE
Requires-Dist: textblob==0.17.1
Requires-Dist: nltk==3.8.1
Requires-Dist: rich==13.7.0
Requires-Dist: pyfiglet==0.8.post1
Dynamic: author
Dynamic: author-email
Dynamic: classifier
Dynamic: description
Dynamic: description-content-type
Dynamic: home-page
Dynamic: license-file
Dynamic: requires-dist
Dynamic: requires-python
Dynamic: summary
